[
  {
    "id": 1,
    "category": "جغرافيا",
    "question": "ما هي عاصمة العراق؟",
    "answers": [
      "بغداد",
      "البصرة",
      "الموصل",
      "أربيل"
    ],
    "correct": 0
  },
  {
    "id": 2,
    "category": "جغرافيا",
    "question": "ما هي عاصمة السعودية؟",
    "answers": [
      "جدة",
      "الرياض",
      "مكة",
      "الدمام"
    ],
    "correct": 1
  },
  {
    "id": 3,
    "category": "جغرافيا",
    "question": "ما هي عاصمة مصر؟",
    "answers": [
      "الإسكندرية",
      "القاهرة",
      "الجيزة",
      "الأقصر"
    ],
    "correct": 1
  },
  {
    "id": 4,
    "category": "جغرافيا",
    "question": "ما أكبر محيط في العالم؟",
    "answers": [
      "الهندي",
      "الأطلسي",
      "الهادئ",
      "المتجمد"
    ],
    "correct": 2
  },
  {
    "id": 5,
    "category": "جغرافيا",
    "question": "في أي قارة تقع البرازيل؟",
    "answers": [
      "آسيا",
      "أوروبا",
      "أمريكا الجنوبية",
      "إفريقيا"
    ],
    "correct": 2
  },
  {
    "id": 6,
    "category": "جغرافيا",
    "question": "ما أطول نهر في العالم؟",
    "answers": [
      "النيل",
      "دجلة",
      "الفرات",
      "الأمازون"
    ],
    "correct": 0
  },
  {
    "id": 7,
    "category": "جغرافيا",
    "question": "ما هي عاصمة الأردن؟",
    "answers": [
      "إربد",
      "عمّان",
      "الزرقاء",
      "العقبة"
    ],
    "correct": 1
  },
  {
    "id": 8,
    "category": "جغرافيا",
    "question": "في أي قارة تقع اليابان؟",
    "answers": [
      "آسيا",
      "أوروبا",
      "إفريقيا",
      "أستراليا"
    ],
    "correct": 0
  },
  {
    "id": 9,
    "category": "جغرافيا",
    "question": "ما هي عاصمة فرنسا؟",
    "answers": [
      "باريس",
      "ليون",
      "مرسيليا",
      "نيس"
    ],
    "correct": 0
  },
  {
    "id": 10,
    "category": "جغرافيا",
    "question": "ما أكبر دولة عربية من حيث المساحة؟",
    "answers": [
      "العراق",
      "السعودية",
      "الجزائر",
      "مصر"
    ],
    "correct": 2
  },
  {
    "id": 11,
    "category": "جغرافيا",
    "question": "ما البحر الذي يطل عليه لبنان؟",
    "answers": [
      "الأحمر",
      "المتوسط",
      "العربي",
      "الميت"
    ],
    "correct": 1
  },
  {
    "id": 12,
    "category": "جغرافيا",
    "question": "أين تقع الأهرامات؟",
    "answers": [
      "العراق",
      "مصر",
      "الأردن",
      "تونس"
    ],
    "correct": 1
  },
  {
    "id": 13,
    "category": "جغرافيا",
    "question": "ما هي عاصمة الإمارات؟",
    "answers": [
      "دبي",
      "أبوظبي",
      "الشارقة",
      "العين"
    ],
    "correct": 1
  },
  {
    "id": 14,
    "category": "جغرافيا",
    "question": "أي دولة تشتهر بمدينة إسطنبول؟",
    "answers": [
      "تركيا",
      "اليونان",
      "إيران",
      "إيطاليا"
    ],
    "correct": 0
  },
  {
    "id": 15,
    "category": "جغرافيا",
    "question": "ما اسم الصحراء الأكبر في العالم؟",
    "answers": [
      "الربع الخالي",
      "الصحراء الكبرى",
      "جوبي",
      "أتاكاما"
    ],
    "correct": 1
  },
  {
    "id": 16,
    "category": "جغرافيا",
    "question": "ما هي عاصمة قطر؟",
    "answers": [
      "الدوحة",
      "المنامة",
      "مسقط",
      "الكويت"
    ],
    "correct": 0
  },
  {
    "id": 17,
    "category": "جغرافيا",
    "question": "في أي قارة تقع أستراليا؟",
    "answers": [
      "آسيا",
      "أوروبا",
      "أوقيانوسيا",
      "إفريقيا"
    ],
    "correct": 2
  },
  {
    "id": 18,
    "category": "جغرافيا",
    "question": "ما هي عاصمة المغرب؟",
    "answers": [
      "الدار البيضاء",
      "الرباط",
      "مراكش",
      "فاس"
    ],
    "correct": 1
  },
  {
    "id": 19,
    "category": "جغرافيا",
    "question": "أي نهر يمر في بغداد؟",
    "answers": [
      "النيل",
      "دجلة",
      "الأردن",
      "العاصي"
    ],
    "correct": 1
  },
  {
    "id": 20,
    "category": "جغرافيا",
    "question": "ما هي عاصمة الكويت؟",
    "answers": [
      "الكويت",
      "حولي",
      "الجهراء",
      "السالمية"
    ],
    "correct": 0
  },
  {
    "id": 21,
    "category": "علوم",
    "question": "كم عدد كواكب المجموعة الشمسية؟",
    "answers": [
      "7",
      "8",
      "9",
      "10"
    ],
    "correct": 1
  },
  {
    "id": 22,
    "category": "علوم",
    "question": "ما الغاز الذي نتنفسه للبقاء على قيد الحياة؟",
    "answers": [
      "الأكسجين",
      "الهيدروجين",
      "النيتروجين",
      "ثاني أكسيد الكربون"
    ],
    "correct": 0
  },
  {
    "id": 23,
    "category": "علوم",
    "question": "ما هو الكوكب الأحمر؟",
    "answers": [
      "المريخ",
      "الزهرة",
      "زحل",
      "عطارد"
    ],
    "correct": 0
  },
  {
    "id": 24,
    "category": "علوم",
    "question": "ما العضو المسؤول عن ضخ الدم؟",
    "answers": [
      "الرئة",
      "القلب",
      "الكبد",
      "المعدة"
    ],
    "correct": 1
  },
  {
    "id": 25,
    "category": "علوم",
    "question": "ما وحدة قياس الحرارة الشائعة؟",
    "answers": [
      "المتر",
      "الكيلوغرام",
      "الدرجة المئوية",
      "اللتر"
    ],
    "correct": 2
  },
  {
    "id": 26,
    "category": "علوم",
    "question": "ما الحيوان المعروف بملك الغابة؟",
    "answers": [
      "النمر",
      "الأسد",
      "الفهد",
      "الدب"
    ],
    "correct": 1
  },
  {
    "id": 27,
    "category": "علوم",
    "question": "ما المادة التي تغطي جسم السمك؟",
    "answers": [
      "الريش",
      "الفرو",
      "القشور",
      "الصوف"
    ],
    "correct": 2
  },
  {
    "id": 28,
    "category": "علوم",
    "question": "ما أكبر عضو في جسم الإنسان؟",
    "answers": [
      "القلب",
      "الكبد",
      "الجلد",
      "الرئة"
    ],
    "correct": 2
  },
  {
    "id": 29,
    "category": "علوم",
    "question": "ما مصدر الطاقة الرئيسي للأرض؟",
    "answers": [
      "القمر",
      "الشمس",
      "الرياح",
      "الماء"
    ],
    "correct": 1
  },
  {
    "id": 30,
    "category": "علوم",
    "question": "ما الكوكب الأقرب إلى الشمس؟",
    "answers": [
      "عطارد",
      "الزهرة",
      "الأرض",
      "المريخ"
    ],
    "correct": 0
  },
  {
    "id": 31,
    "category": "علوم",
    "question": "ما اسم العملية التي يصنع بها النبات غذاءه؟",
    "answers": [
      "التنفس",
      "البناء الضوئي",
      "الهضم",
      "التبخر"
    ],
    "correct": 1
  },
  {
    "id": 32,
    "category": "علوم",
    "question": "كم عدد أرجل العنكبوت؟",
    "answers": [
      "6",
      "8",
      "10",
      "12"
    ],
    "correct": 1
  },
  {
    "id": 33,
    "category": "علوم",
    "question": "ما الغاز الذي يخرجه الإنسان عند الزفير؟",
    "answers": [
      "الأكسجين",
      "ثاني أكسيد الكربون",
      "الهيدروجين",
      "الهيليوم"
    ],
    "correct": 1
  },
  {
    "id": 34,
    "category": "علوم",
    "question": "ما حالة الماء عند درجة 0 مئوية؟",
    "answers": [
      "يغلي",
      "يتجمد",
      "يتبخر",
      "يتحول لغاز"
    ],
    "correct": 1
  },
  {
    "id": 35,
    "category": "علوم",
    "question": "ما الجهاز المسؤول عن التفكير؟",
    "answers": [
      "القلب",
      "الدماغ",
      "الرئة",
      "الكلى"
    ],
    "correct": 1
  },
  {
    "id": 36,
    "category": "علوم",
    "question": "ما لون الدم في جسم الإنسان؟",
    "answers": [
      "أحمر",
      "أزرق",
      "أخضر",
      "أصفر"
    ],
    "correct": 0
  },
  {
    "id": 37,
    "category": "علوم",
    "question": "ما الحيوان الذي يلقب بسفينة الصحراء؟",
    "answers": [
      "الحصان",
      "الجمل",
      "الفيل",
      "الغزال"
    ],
    "correct": 1
  },
  {
    "id": 38,
    "category": "علوم",
    "question": "ما المعدن السائل في درجة حرارة الغرفة؟",
    "answers": [
      "الحديد",
      "النحاس",
      "الزئبق",
      "الذهب"
    ],
    "correct": 2
  },
  {
    "id": 39,
    "category": "علوم",
    "question": "كم عدد حواس الإنسان الأساسية؟",
    "answers": [
      "4",
      "5",
      "6",
      "7"
    ],
    "correct": 1
  },
  {
    "id": 40,
    "category": "علوم",
    "question": "ما الكوكب الذي نعيش عليه؟",
    "answers": [
      "المريخ",
      "الأرض",
      "زحل",
      "المشتري"
    ],
    "correct": 1
  },
  {
    "id": 41,
    "category": "تاريخ",
    "question": "أين وُجدت حضارة وادي الرافدين؟",
    "answers": [
      "العراق",
      "مصر",
      "اليمن",
      "المغرب"
    ],
    "correct": 0
  },
  {
    "id": 42,
    "category": "تاريخ",
    "question": "من بنى الأهرامات؟",
    "answers": [
      "الإغريق",
      "الفراعنة",
      "الرومان",
      "الفرس"
    ],
    "correct": 1
  },
  {
    "id": 43,
    "category": "تاريخ",
    "question": "في أي بلد وُلدت الكتابة المسمارية؟",
    "answers": [
      "العراق",
      "مصر",
      "الصين",
      "الهند"
    ],
    "correct": 0
  },
  {
    "id": 44,
    "category": "تاريخ",
    "question": "ما اسم عاصمة الدولة العباسية القديمة؟",
    "answers": [
      "دمشق",
      "بغداد",
      "القاهرة",
      "قرطبة"
    ],
    "correct": 1
  },
  {
    "id": 45,
    "category": "تاريخ",
    "question": "من هو أول الخلفاء الراشدين؟",
    "answers": [
      "عمر بن الخطاب",
      "أبو بكر الصديق",
      "عثمان بن عفان",
      "علي بن أبي طالب"
    ],
    "correct": 1
  },
  {
    "id": 46,
    "category": "تاريخ",
    "question": "أي مدينة كانت عاصمة الأندلس لفترة طويلة؟",
    "answers": [
      "غرناطة",
      "قرطبة",
      "إشبيلية",
      "مدريد"
    ],
    "correct": 1
  },
  {
    "id": 47,
    "category": "تاريخ",
    "question": "من اخترع المصباح الكهربائي تجاريًا؟",
    "answers": [
      "إديسون",
      "نيوتن",
      "أينشتاين",
      "غراهام بل"
    ],
    "correct": 0
  },
  {
    "id": 48,
    "category": "تاريخ",
    "question": "في أي بلد قامت الحضارة الفرعونية؟",
    "answers": [
      "العراق",
      "مصر",
      "سوريا",
      "تركيا"
    ],
    "correct": 1
  },
  {
    "id": 49,
    "category": "تاريخ",
    "question": "ما اسم السفينة الشهيرة التي غرقت عام 1912؟",
    "answers": [
      "تيتانيك",
      "فيكتوريا",
      "سانتا ماريا",
      "كوين ماري"
    ],
    "correct": 0
  },
  {
    "id": 50,
    "category": "تاريخ",
    "question": "من هو القائد الذي فتح القسطنطينية؟",
    "answers": [
      "صلاح الدين",
      "محمد الفاتح",
      "هارون الرشيد",
      "طارق بن زياد"
    ],
    "correct": 1
  },
  {
    "id": 51,
    "category": "تاريخ",
    "question": "ما اسم أول إنسان صعد إلى الفضاء؟",
    "answers": [
      "نيل آرمسترونغ",
      "يوري غاغارين",
      "ألبرت أينشتاين",
      "ماجلان"
    ],
    "correct": 1
  },
  {
    "id": 52,
    "category": "تاريخ",
    "question": "في أي دولة ظهرت الألعاب الأولمبية القديمة؟",
    "answers": [
      "إيطاليا",
      "اليونان",
      "مصر",
      "الصين"
    ],
    "correct": 1
  },
  {
    "id": 53,
    "category": "تاريخ",
    "question": "من هو مخترع الهاتف؟",
    "answers": [
      "غراهام بل",
      "إديسون",
      "نيوتن",
      "تسلا"
    ],
    "correct": 0
  },
  {
    "id": 54,
    "category": "تاريخ",
    "question": "ما المدينة التي كانت عاصمة الأمويين؟",
    "answers": [
      "بغداد",
      "دمشق",
      "القاهرة",
      "مكة"
    ],
    "correct": 1
  },
  {
    "id": 55,
    "category": "تاريخ",
    "question": "ما اسم القائد المسلم في معركة حطين؟",
    "answers": [
      "صلاح الدين الأيوبي",
      "خالد بن الوليد",
      "عمرو بن العاص",
      "طارق بن زياد"
    ],
    "correct": 0
  },
  {
    "id": 56,
    "category": "تاريخ",
    "question": "ما الحضارة التي اشتهرت بالحدائق المعلقة؟",
    "answers": [
      "البابلية",
      "الرومانية",
      "الفارسية",
      "اليونانية"
    ],
    "correct": 0
  },
  {
    "id": 57,
    "category": "تاريخ",
    "question": "من هو أول رئيس للولايات المتحدة؟",
    "answers": [
      "لينكولن",
      "واشنطن",
      "روزفلت",
      "جيفرسون"
    ],
    "correct": 1
  },
  {
    "id": 58,
    "category": "تاريخ",
    "question": "ما البلد الذي خرجت منه الثورة الصناعية؟",
    "answers": [
      "فرنسا",
      "ألمانيا",
      "بريطانيا",
      "إسبانيا"
    ],
    "correct": 2
  },
  {
    "id": 59,
    "category": "تاريخ",
    "question": "ما اسم أول مسجد بُني في الإسلام؟",
    "answers": [
      "قباء",
      "الأقصى",
      "الحرام",
      "النبوي"
    ],
    "correct": 0
  },
  {
    "id": 60,
    "category": "تاريخ",
    "question": "ما اسم المدينة التي هاجر إليها النبي محمد ﷺ؟",
    "answers": [
      "مكة",
      "المدينة",
      "الطائف",
      "بدر"
    ],
    "correct": 1
  },
  {
    "id": 61,
    "category": "رياضة",
    "question": "كم لاعبًا يوجد في فريق كرة القدم داخل الملعب؟",
    "answers": [
      "10",
      "11",
      "12",
      "9"
    ],
    "correct": 1
  },
  {
    "id": 62,
    "category": "رياضة",
    "question": "كم دقيقة مدة مباراة كرة القدم الأصلية؟",
    "answers": [
      "60",
      "75",
      "90",
      "120"
    ],
    "correct": 2
  },
  {
    "id": 63,
    "category": "رياضة",
    "question": "ما الرياضة التي يستخدم فيها المضرب والكرة الصفراء؟",
    "answers": [
      "التنس",
      "السباحة",
      "الملاكمة",
      "الجري"
    ],
    "correct": 0
  },
  {
    "id": 64,
    "category": "رياضة",
    "question": "كم عدد حلقات شعار الألعاب الأولمبية؟",
    "answers": [
      "4",
      "5",
      "6",
      "7"
    ],
    "correct": 1
  },
  {
    "id": 65,
    "category": "رياضة",
    "question": "ما الرياضة التي تُلعب على الجليد بعصا وقرص؟",
    "answers": [
      "هوكي الجليد",
      "التنس",
      "البيسبول",
      "كرة اليد"
    ],
    "correct": 0
  },
  {
    "id": 66,
    "category": "رياضة",
    "question": "كم شوط في مباراة كرة القدم؟",
    "answers": [
      "1",
      "2",
      "3",
      "4"
    ],
    "correct": 1
  },
  {
    "id": 67,
    "category": "رياضة",
    "question": "ما لون البطاقة التي تعني طرد اللاعب في كرة القدم؟",
    "answers": [
      "صفراء",
      "حمراء",
      "خضراء",
      "زرقاء"
    ],
    "correct": 1
  },
  {
    "id": 68,
    "category": "رياضة",
    "question": "ما الرياضة التي يشتهر بها محمد علي كلاي؟",
    "answers": [
      "كرة القدم",
      "الملاكمة",
      "التنس",
      "السلة"
    ],
    "correct": 1
  },
  {
    "id": 69,
    "category": "رياضة",
    "question": "كم لاعبًا في فريق كرة السلة داخل الملعب؟",
    "answers": [
      "4",
      "5",
      "6",
      "7"
    ],
    "correct": 1
  },
  {
    "id": 70,
    "category": "رياضة",
    "question": "ما الرياضة التي تستخدم فيها الشبكة والكرة فوقها؟",
    "answers": [
      "الطائرة",
      "الجولف",
      "المصارعة",
      "الرماية"
    ],
    "correct": 0
  },
  {
    "id": 71,
    "category": "رياضة",
    "question": "ما اسم البطولة العالمية لكرة القدم؟",
    "answers": [
      "كأس العالم",
      "الدوري",
      "الكأس المحلي",
      "السوبر"
    ],
    "correct": 0
  },
  {
    "id": 72,
    "category": "رياضة",
    "question": "ما الرياضة التي تُلعب في الماء وتحتاج سباحة؟",
    "answers": [
      "الملاكمة",
      "كرة الماء",
      "الجري",
      "التنس"
    ],
    "correct": 1
  },
  {
    "id": 73,
    "category": "رياضة",
    "question": "في كرة القدم، من يحرس المرمى؟",
    "answers": [
      "المدافع",
      "الحارس",
      "المهاجم",
      "الحكم"
    ],
    "correct": 1
  },
  {
    "id": 74,
    "category": "رياضة",
    "question": "ما الأداة الأساسية في رياضة الجولف؟",
    "answers": [
      "مضرب",
      "قفاز",
      "خوذة",
      "شبكة"
    ],
    "correct": 0
  },
  {
    "id": 75,
    "category": "رياضة",
    "question": "ما الرياضة التي تعتمد على رمي الكرة في السلة؟",
    "answers": [
      "كرة السلة",
      "اليد",
      "القدم",
      "الطائرة"
    ],
    "correct": 0
  },
  {
    "id": 76,
    "category": "رياضة",
    "question": "كم نقطة تسجل الرمية الحرة في كرة السلة؟",
    "answers": [
      "1",
      "2",
      "3",
      "4"
    ],
    "correct": 0
  },
  {
    "id": 77,
    "category": "رياضة",
    "question": "ما الرياضة التي يستخدم فيها القوس والسهم؟",
    "answers": [
      "الرماية",
      "السباحة",
      "الجودو",
      "الجري"
    ],
    "correct": 0
  },
  {
    "id": 78,
    "category": "رياضة",
    "question": "ما اسم الحكم في كرة القدم بالإنجليزية؟",
    "answers": [
      "Coach",
      "Referee",
      "Player",
      "Captain"
    ],
    "correct": 1
  },
  {
    "id": 79,
    "category": "رياضة",
    "question": "ما الرياضة التي تُلعب على طاولة صغيرة بمضارب؟",
    "answers": [
      "تنس الطاولة",
      "الجولف",
      "الهوكي",
      "الركبي"
    ],
    "correct": 0
  },
  {
    "id": 80,
    "category": "رياضة",
    "question": "من يفوز في السباق؟",
    "answers": [
      "الأبطأ",
      "الأسرع",
      "الأطول",
      "الأثقل"
    ],
    "correct": 1
  },
  {
    "id": 81,
    "category": "تقنية",
    "question": "من الشركة المطورة لنظام أندرويد؟",
    "answers": [
      "Apple",
      "Microsoft",
      "Google",
      "Samsung"
    ],
    "correct": 2
  },
  {
    "id": 82,
    "category": "تقنية",
    "question": "ما معنى Wi-Fi؟",
    "answers": [
      "شبكة لاسلكية",
      "سلك كهرباء",
      "نوع طابعة",
      "ملف صوت"
    ],
    "correct": 0
  },
  {
    "id": 83,
    "category": "تقنية",
    "question": "ما الجهاز المستخدم للكتابة على الحاسوب؟",
    "answers": [
      "الشاشة",
      "لوحة المفاتيح",
      "السماعة",
      "الطابعة"
    ],
    "correct": 1
  },
  {
    "id": 84,
    "category": "تقنية",
    "question": "ما المتصفح التابع لشركة Google؟",
    "answers": [
      "Chrome",
      "Safari",
      "Firefox",
      "Edge"
    ],
    "correct": 0
  },
  {
    "id": 85,
    "category": "تقنية",
    "question": "ما نظام تشغيل هواتف iPhone؟",
    "answers": [
      "Android",
      "Windows",
      "iOS",
      "Linux"
    ],
    "correct": 2
  },
  {
    "id": 86,
    "category": "تقنية",
    "question": "ما معنى CPU؟",
    "answers": [
      "المعالج",
      "الشاشة",
      "الذاكرة الخارجية",
      "البطارية"
    ],
    "correct": 0
  },
  {
    "id": 87,
    "category": "تقنية",
    "question": "ما وظيفة كلمة المرور؟",
    "answers": [
      "تغيير اللون",
      "حماية الحساب",
      "تشغيل الصوت",
      "طباعة الصور"
    ],
    "correct": 1
  },
  {
    "id": 88,
    "category": "تقنية",
    "question": "ما الجهاز الذي يربطك بالإنترنت غالبًا في البيت؟",
    "answers": [
      "الراوتر",
      "الطابعة",
      "الكاميرا",
      "السماعة"
    ],
    "correct": 0
  },
  {
    "id": 89,
    "category": "تقنية",
    "question": "ما نوع الملف الذي ينتهي بـ .jpg غالبًا؟",
    "answers": [
      "صورة",
      "صوت",
      "فيديو",
      "برنامج"
    ],
    "correct": 0
  },
  {
    "id": 90,
    "category": "تقنية",
    "question": "ما نوع الملف الذي ينتهي بـ .mp3 غالبًا؟",
    "answers": [
      "صورة",
      "صوت",
      "نص",
      "جدول"
    ],
    "correct": 1
  },
  {
    "id": 91,
    "category": "تقنية",
    "question": "ما وظيفة الماوس؟",
    "answers": [
      "إدخال وتحريك المؤشر",
      "حفظ الملفات",
      "تبريد الجهاز",
      "شحن الهاتف"
    ],
    "correct": 0
  },
  {
    "id": 92,
    "category": "تقنية",
    "question": "ما التطبيق المعروف للمحادثات في ديسكورد؟",
    "answers": [
      "Discord",
      "Excel",
      "Photoshop",
      "PowerPoint"
    ],
    "correct": 0
  },
  {
    "id": 93,
    "category": "تقنية",
    "question": "ما معنى RAM؟",
    "answers": [
      "ذاكرة مؤقتة",
      "شاشة",
      "كاميرا",
      "بطارية"
    ],
    "correct": 0
  },
  {
    "id": 94,
    "category": "تقنية",
    "question": "ما الشركة المطورة لنظام Windows؟",
    "answers": [
      "Apple",
      "Microsoft",
      "Google",
      "Sony"
    ],
    "correct": 1
  },
  {
    "id": 95,
    "category": "تقنية",
    "question": "ما خدمة البريد التابعة لـ Google؟",
    "answers": [
      "Gmail",
      "Outlook",
      "Yahoo",
      "iCloud"
    ],
    "correct": 0
  },
  {
    "id": 96,
    "category": "تقنية",
    "question": "ما وظيفة الكاميرا؟",
    "answers": [
      "التصوير",
      "الطباعة",
      "التبريد",
      "الشحن"
    ],
    "correct": 0
  },
  {
    "id": 97,
    "category": "تقنية",
    "question": "ما معنى USB؟",
    "answers": [
      "منفذ توصيل",
      "برنامج رسم",
      "نوع شاشة",
      "ملف صوت"
    ],
    "correct": 0
  },
  {
    "id": 98,
    "category": "تقنية",
    "question": "ما التطبيق الشهير لمشاركة الفيديوهات القصيرة؟",
    "answers": [
      "TikTok",
      "Excel",
      "Word",
      "Teams"
    ],
    "correct": 0
  },
  {
    "id": 99,
    "category": "تقنية",
    "question": "ما الجهاز الذي تستخدمه لإخراج الصوت؟",
    "answers": [
      "السماعات",
      "الطابعة",
      "الماوس",
      "الكيبورد"
    ],
    "correct": 0
  },
  {
    "id": 100,
    "category": "تقنية",
    "question": "ما فائدة النسخ الاحتياطي؟",
    "answers": [
      "حفظ نسخة من البيانات",
      "حذف الصور",
      "إطفاء الجهاز",
      "زيادة الصوت"
    ],
    "correct": 0
  }
]